piper_onnx/__init__.py
piper_onnx/py.typed
piper_onnx-1.0.5.dist-info/METADATA
piper_onnx-1.0.5.dist-info/WHEEL
piper_onnx-1.0.5.dist-info/licenses/LICENSE
piper_onnx-1.0.5.dist-info/RECORD
