Metadata-Version: 2.4
Name: piper-onnx
Version: 1.0.5
Summary: Use piper TTS with onnxruntime
Project-URL: Homepage, https://github.com/thewh1teagle/piper-onnx
Project-URL: Repository, https://github.com/thewh1teagle/piper-onnx
Project-URL: Issues, https://github.com/thewh1teagle/piper-onnx/issues
Author-email: thewh1teagle <61390950+thewh1teagle@users.noreply.github.com>
License: MIT License
License-File: LICENSE
Requires-Python: >=3.10
Requires-Dist: espeakng-loader>=0.2.4
Requires-Dist: onnxruntime>=1.20.0
Requires-Dist: phonemizer-fork>=3.3.2
